pygfunction/__init__.py
pygfunction/_mpl.py
pygfunction/borefield.py
pygfunction/boreholes.py
pygfunction/gfunction.py
pygfunction/heat_transfer.py
pygfunction/load_aggregation.py
pygfunction/media.py
pygfunction/networks.py
pygfunction/pipes.py
pygfunction/utilities.py
pygfunction-2.3.0.dist-info/licenses/LICENSE.md
pygfunction-2.3.0.dist-info/METADATA
pygfunction-2.3.0.dist-info/WHEEL
pygfunction-2.3.0.dist-info/top_level.txt
pygfunction-2.3.0.dist-info/RECORD
