Metadata-Version: 2.4
Name: pygfunction
Version: 2.3.0
Summary: A g-function calculator for Python
Home-page: https://github.com/MassimoCimmino/pygfunction
Author: Massimo Cimmino
Author-email: massimo.cimmino@polymtl.ca
License: BSD 3-Clause License
Keywords: Geothermal,Ground-source,Ground heat exchangers
Classifier: Development Status :: 5 - Production/Stable
Classifier: Intended Audience :: Science/Research
Classifier: License :: OSI Approved :: BSD License
Classifier: Natural Language :: English
Classifier: Operating System :: OS Independent
Classifier: Programming Language :: Python :: 3
Classifier: Programming Language :: Python :: 3 :: Only
Classifier: Programming Language :: Python :: 3.9
Classifier: Topic :: Scientific/Engineering
Classifier: Topic :: Utilities
Requires-Python: >=3.9
License-File: LICENSE.md
Requires-Dist: numpy>=1.26.4
Requires-Dist: scipy>=1.13.1
Requires-Dist: secondarycoolantprops>=1.3
Requires-Dist: typing_extensions>=4.11.0
Provides-Extra: doc
Requires-Dist: numpydoc>=1.7.0; extra == "doc"
Requires-Dist: recommonmark>=0.7.1; extra == "doc"
Requires-Dist: sphinx>=7.3.7; extra == "doc"
Provides-Extra: plot
Requires-Dist: matplotlib>=3.9.2; extra == "plot"
Provides-Extra: testing
Requires-Dist: matplotlib>=3.9.2; extra == "testing"
Requires-Dist: pytest>=7.4.4; extra == "testing"
Requires-Dist: pytest-cov>=6.1.1; extra == "testing"
Requires-Dist: tox>=4.25.0; extra == "testing"
Dynamic: license-file
